pqpopups/ComSound.py
pqpopups/PQPopupDef.py
pqpopups/PQPopupKeypad_widget_1280x800.py
pqpopups/PQPopupMessage_widget_1280x800.py
pqpopups/PQPopupNumpad_simple_widget_1280x800.py
pqpopups/PQPopupNumpad_widget_1280x800.py
pqpopups/__init__.py
pqpopups-1.0.11.dist-info/METADATA
pqpopups-1.0.11.dist-info/WHEEL
pqpopups-1.0.11.dist-info/top_level.txt
pqpopups-1.0.11.dist-info/RECORD
